math_tokenizer-1.0.1.dist-info/DESCRIPTION.rst
math_tokenizer-1.0.1.dist-info/METADATA
math_tokenizer-1.0.1.dist-info/RECORD
math_tokenizer-1.0.1.dist-info/WHEEL
math_tokenizer-1.0.1.dist-info/metadata.json
math_tokenizer-1.0.1.dist-info/top_level.txt
tokenizer/__init__.py
tokenizer/tokenizer.py
