Metadata-Version: 2.0
Name: math-tokenizer
Version: 1.0.1
Summary: Simple and lightweighted tokenizer for mathematical functions
Home-page: https://github.com/DahlitzFlorian/math-tokenizer
Author: Florian Dahlitz
Author-email: f2dahlitz@freenet.de
License: MIT
Keywords: tokenizer math math-functions token analysis
Platform: UNKNOWN
Classifier: Development Status :: 3 - Alpha
Classifier: Intended Audience :: Developers
Classifier: License :: OSI Approved :: MIT License
Classifier: Programming Language :: Python :: 3.4
Classifier: Programming Language :: Python :: 3.5
Classifier: Programming Language :: Python :: 3.6
